<ui:UiBinder xmlns:ui='urn:ui:com.google.gwt.uibinder'
             xmlns:g='urn:import:com.google.gwt.user.client.ui'
             xmlns:c='urn:import:com.google.gwt.user.cellview.client'>
        <g:DecoratorPanel>
                <g:VerticalPanel spacing="10">
                        <c:CellTable ui:field="table" width="100%" pageSize="15">
                        </c:CellTable>
                        <g:Button ui:field="createTask">Создать новую задачу</g:Button>
                </g:VerticalPanel>
        </g:DecoratorPanel>
</ui:UiBinder>